LICENSE
MANIFEST.in
README.md
setup.cfg
setup.py
pgpart/__init__.py
pgpart/cli.py
pgpart/listp.py
pgpart/rangep.py
pgpart.egg-info/PKG-INFO
pgpart.egg-info/SOURCES.txt
pgpart.egg-info/dependency_links.txt
pgpart.egg-info/entry_points.txt
pgpart.egg-info/not-zip-safe
pgpart.egg-info/requires.txt
pgpart.egg-info/top_level.txt
requirements/common.txt
requirements/development.txt
requirements/test.txt
tests/.coverage
tests/test_range.py
tests/.cache/v/cache/lastfailed
tests/htmlcov/coverage_html.js
tests/htmlcov/index.html
tests/htmlcov/jquery.debounce.min.js
tests/htmlcov/jquery.hotkeys.js
tests/htmlcov/jquery.isonscreen.js
tests/htmlcov/jquery.min.js
tests/htmlcov/jquery.tablesorter.min.js
tests/htmlcov/keybd_closed.png
tests/htmlcov/keybd_open.png
tests/htmlcov/status.json
tests/htmlcov/style.css
tests/htmlcov/test_range_py.html