Metadata-Version: 1.1
Name: pgpart
Version: 0.1.0
Summary: Generate PostgreSQL partitioned table DDL
Home-page: https://github.com/achiku/pgpart
Author: Akira Chiku
Author-email: akira.chiku@gmail.com
License: MIT
Platform: any
Classifier: Development Status :: 1 - Planning
Classifier: Environment :: Console
Classifier: Intended Audience :: Developers
Classifier: License :: OSI Approved :: MIT License
Classifier: Operating System :: POSIX
Classifier: Operating System :: MacOS
Classifier: Operating System :: Unix
Classifier: Programming Language :: Python :: 2.7
Classifier: Programming Language :: Python :: 3.4
Classifier: Programming Language :: Python :: 3.5
Classifier: Topic :: Software Development :: Libraries :: Python Modules
